{
  "ok": true,
  "count": 4,
  "accountsWithPosts": 4,
  "fetchedAt": "2026-06-16T16:29:44.769165+00:00",
  "windowHours": 4,
  "curation": "guaranteed3_engagement1",
  "errors": [],
  "posts": [
    {
      "id": "2066913971186143608",
      "text": "Is The 'Compute Is Scarce' Narrative Starting To Crack? https://www.zerohedge.com/markets/compute-scarce-narrative-starting-crack",
      "author": "zerohedge",
      "handle": "zerohedge",
      "createdAt": "2026-06-16T16:01:06+00:00",
      "createdAtMs": 1781625666000,
      "likes": 0,
      "retweets": 0,
      "url": "https://x.com/zerohedge/status/2066913971186143608#m",
      "avatar": null,
      "slot": "guaranteed",
      "slot_order": 1
    },
    {
      "id": "2066918774914138619",
      "text": "After arriving in America in 1831, Alexis de Tocqueville visited Sing Sing, what was then the country’s biggest prison, to write a report on the American penal system. For episode two of “Tocqueville Road Trip” we returned. Listen now https://www.economist.com/podcasts/2026/06/11/2-against-all-obstacles?taid=6a3177bcd8e6d40001a4465e&utm_campaign=trueanthem&utm_medium=social&utm_source=twitter",
      "author": "TheEconomist",
      "handle": "TheEconomist",
      "createdAt": "2026-06-16T16:20:12+00:00",
      "createdAtMs": 1781626812000,
      "likes": 0,
      "retweets": 0,
      "url": "https://x.com/TheEconomist/status/2066918774914138619#m",
      "avatar": null,
      "slot": "guaranteed",
      "slot_order": 2
    },
    {
      "id": "2066914695274012857",
      "text": "BREAKING: The US will allow Iran to immediately begin selling oil and fuel under the deal to end the war, per WSJ.\n\nDetails include:\n\n1. The provision for waivers of sanctions on oil sales takes effect immediately upon signing the agreement\n\n2. This also covers necessary services including banking, transportation and insurance needed to facilitate the sales\n\n3. Iran is expected to receive upfront sanctions relief under the deal with further relief tied to Iran’s performance\n\nOil prices are down sharply on the news.",
      "author": "KobeissiLetter",
      "handle": "KobeissiLetter",
      "createdAt": "2026-06-16T16:03:59+00:00",
      "createdAtMs": 1781625839000,
      "likes": 0,
      "retweets": 0,
      "url": "https://x.com/KobeissiLetter/status/2066914695274012857#m",
      "avatar": null,
      "slot": "guaranteed",
      "slot_order": 3
    },
    {
      "id": "2066874913260978538",
      "text": "(1) HydroGraph Clean Power Inc. has announced an official partnership with Modern Dispersions, Inc. (MDI), where MDI is certified as a qualified compounding partner for large-scale graphene production in North America. >>>>>>>>",
      "author": "BambroughKevin",
      "handle": "BambroughKevin",
      "createdAt": "2026-06-16T13:25:54+00:00",
      "createdAtMs": 1781616354000,
      "likes": 0,
      "retweets": 0,
      "url": "https://x.com/HenschenMarten/status/2066874913260978538#m",
      "avatar": null,
      "slot": "engagement",
      "slot_order": 4
    }
  ]
}