{
  "ok": true,
  "count": 4,
  "accountsWithPosts": 4,
  "fetchedAt": "2026-05-30T00:01:12.849787+00:00",
  "windowHours": 4,
  "curation": "guaranteed3_engagement1",
  "errors": [],
  "posts": [
    {
      "id": "2060506502742352349",
      "text": "US Service Members Targeted Via Commercial Location Data, Pentagon Tells Senators https://www.zerohedge.com/military/us-service-members-targeted-commercial-location-data-pentagon-tells-senators",
      "author": "zerohedge",
      "handle": "zerohedge",
      "createdAt": "2026-05-29T23:40:07+00:00",
      "createdAtMs": 1780098007000,
      "likes": 0,
      "retweets": 0,
      "url": "https://x.com/zerohedge/status/2060506502742352349#m",
      "avatar": null,
      "slot": "guaranteed",
      "slot_order": 1
    },
    {
      "id": "2060506516776505392",
      "text": "As America’s war on Iran roils energy markets, China’s clean-energy companies should be cashing in. Register for free to learn why they are in turmoil instead https://www.economist.com/china/2026/05/26/chinas-world-beating-solar-industry-is-in-turmoil?taid=6a1a23da16ca9c0001d5a429&utm_campaign=trueanthem&utm_medium=social&utm_source=twitter",
      "author": "TheEconomist",
      "handle": "TheEconomist",
      "createdAt": "2026-05-29T23:40:10+00:00",
      "createdAtMs": 1780098010000,
      "likes": 0,
      "retweets": 0,
      "url": "https://x.com/TheEconomist/status/2060506516776505392#m",
      "avatar": null,
      "slot": "guaranteed",
      "slot_order": 2
    },
    {
      "id": "2060486641634910499",
      "text": "AI is about to reshape the global workforce:\n\n24% of jobs globally, or ~838 million positions, are estimated to be exposed to generative AI.\n\nHigh-income countries are facing the greatest risk at ~33% of employment, with ~6% of roles potentially having the highest exposure.\n\nJobs with the highest exposure are those with repetitive and predictable tasks, meaning AI can automate them with little human variability required.\n\nBy comparison, the exposure of low-income countries is ~11% or one-third the levels of high-income countries.\n\nEurope and Central Asia are the most exposed regions at ~32% of employment, followed by the Americas at ~30%, while Africa is the least exposed at ~13%.\n\nThe biggest workforce transformation in modern history is underway.",
      "author": "KobeissiLetter",
      "handle": "KobeissiLetter",
      "createdAt": "2026-05-29T22:21:12+00:00",
      "createdAtMs": 1780093272000,
      "likes": 0,
      "retweets": 0,
      "url": "https://x.com/KobeissiLetter/status/2060486641634910499#m",
      "avatar": null,
      "slot": "guaranteed",
      "slot_order": 3
    },
    {
      "id": "2060441185060003927",
      "text": "“So I get that your energy fund got flat-footed by COVID, but how did you lose this much as inventory drew 12mm bbl/d??”\n\nBet this is gonna be the first question for every energy GP during a DD call for the rest of this decade…",
      "author": "hkuppy",
      "handle": "hkuppy",
      "createdAt": "2026-05-29T19:20:34+00:00",
      "createdAtMs": 1780082434000,
      "likes": 0,
      "retweets": 0,
      "url": "https://x.com/hkuppy/status/2060441185060003927#m",
      "avatar": null,
      "slot": "engagement",
      "slot_order": 4
    }
  ]
}