{
  "ok": true,
  "count": 4,
  "accountsWithPosts": 4,
  "fetchedAt": "2026-03-13T08:01:59.146759+00:00",
  "windowHours": 4,
  "curation": "guaranteed3_engagement1",
  "errors": [],
  "posts": [
    {
      "id": "2032358529617551368",
      "text": "Germany's Industrial Collapse: Degrowth And Ideology At Work https://www.zerohedge.com/economics/germanys-industrial-collapse-degrowth-and-ideology-work",
      "author": "zerohedge",
      "handle": "zerohedge",
      "createdAt": "2026-03-13T07:30:07+00:00",
      "createdAtMs": 1773387007000,
      "likes": 0,
      "retweets": 0,
      "url": "https://x.com/zerohedge/status/2032358529617551368#m",
      "avatar": null,
      "slot": "guaranteed",
      "slot_order": 1
    },
    {
      "id": "2032361047554675050",
      "text": "What started as a local journalism trope has become a governing philosophy, turning Britain into a land where no one can ever lose out. The country wants compensation, for everything https://www.economist.com/britain/2026/03/12/how-britain-became-a-compo-nation?taid=69b3bf57e4ff7500010019dc&utm_campaign=trueanthem&utm_medium=social&utm_source=twitter",
      "author": "TheEconomist",
      "handle": "TheEconomist",
      "createdAt": "2026-03-13T07:40:07+00:00",
      "createdAtMs": 1773387607000,
      "likes": 0,
      "retweets": 0,
      "url": "https://x.com/TheEconomist/status/2032361047554675050#m",
      "avatar": null,
      "slot": "guaranteed",
      "slot_order": 2
    },
    {
      "id": "2032311438937579896",
      "text": "BREAKING: The head of CME Group has warned the Trump Administration it risks a “biblical disaster” if it attempts to lower oil prices by intervening in derivatives markets during the war with Iran.",
      "author": "KobeissiLetter",
      "handle": "KobeissiLetter",
      "createdAt": "2026-03-13T04:23:00+00:00",
      "createdAtMs": 1773375780000,
      "likes": 0,
      "retweets": 0,
      "url": "https://x.com/KobeissiLetter/status/2032311438937579896#m",
      "avatar": null,
      "slot": "guaranteed",
      "slot_order": 3
    },
    {
      "id": "2032132039919780046",
      "text": "\"Capital markets reward you for what you learn that other people have yet to ascertain.\"\n\n- Kenneth C. Griffin:",
      "author": "BambroughKevin",
      "handle": "BambroughKevin",
      "createdAt": "2026-03-12T16:30:08+00:00",
      "createdAtMs": 1773333008000,
      "likes": 0,
      "retweets": 0,
      "url": "https://x.com/GoshawkTrades/status/2032132039919780046#m",
      "avatar": null,
      "slot": "engagement",
      "slot_order": 4
    }
  ]
}