{
  "ok": true,
  "count": 4,
  "accountsWithPosts": 4,
  "fetchedAt": "2026-05-26T16:01:10.521772+00:00",
  "windowHours": 4,
  "curation": "guaranteed3_engagement1",
  "errors": [],
  "posts": [
    {
      "id": "2059298542691185100",
      "text": "AI Rally Triggers Best Run In Global Momentum Stocks On Record https://www.zerohedge.com/markets/ai-rally-drives-best-run-global-momentum-stocks-record",
      "author": "zerohedge",
      "handle": "zerohedge",
      "createdAt": "2026-05-26T15:40:07+00:00",
      "createdAtMs": 1779810007000,
      "likes": 0,
      "retweets": 0,
      "url": "https://x.com/zerohedge/status/2059298542691185100#m",
      "avatar": null,
      "slot": "guaranteed",
      "slot_order": 1
    },
    {
      "id": "2059298539319046542",
      "text": "Increasingly, Ethiopians of all stripes resent the prime minister for amassing too much power. That will not stop him from being re-elected https://www.economist.com/middle-east-and-africa/2026/05/25/abiy-ahmed-dreams-of-remaking-ethiopia-in-his-image?taid=6a15bed6804c350001606323&utm_campaign=trueanthem&utm_medium=social&utm_source=twitter",
      "author": "TheEconomist",
      "handle": "TheEconomist",
      "createdAt": "2026-05-26T15:40:06+00:00",
      "createdAtMs": 1779810006000,
      "likes": 0,
      "retweets": 0,
      "url": "https://x.com/TheEconomist/status/2059298539319046542#m",
      "avatar": null,
      "slot": "guaranteed",
      "slot_order": 2
    },
    {
      "id": "2059285642949919166",
      "text": "BREAKING: Micron stock, $MU, officially hits $1 trillion in market cap for the first time in history. \n\n12 months ago, this stock was worth just $70 billion.",
      "author": "KobeissiLetter",
      "handle": "KobeissiLetter",
      "createdAt": "2026-05-26T14:48:51+00:00",
      "createdAtMs": 1779806931000,
      "likes": 0,
      "retweets": 0,
      "url": "https://x.com/KobeissiLetter/status/2059285642949919166#m",
      "avatar": null,
      "slot": "guaranteed",
      "slot_order": 3
    },
    {
      "id": "2058995620363292923",
      "text": "Dramatic improvements…",
      "author": "BambroughKevin",
      "handle": "BambroughKevin",
      "createdAt": "2026-05-25T19:36:24+00:00",
      "createdAtMs": 1779737784000,
      "likes": 0,
      "retweets": 0,
      "url": "https://x.com/BambroughKevin/status/2058995620363292923#m",
      "avatar": null,
      "slot": "engagement",
      "slot_order": 4
    }
  ]
}