{
  "ok": true,
  "count": 4,
  "accountsWithPosts": 4,
  "fetchedAt": "2026-03-29T16:00:56.645408+00:00",
  "windowHours": 4,
  "curation": "guaranteed3_engagement1",
  "errors": [],
  "posts": [
    {
      "id": "2038280048008913157",
      "text": "I'm Sorry, But The Fed Has Run Out Of Road https://www.zerohedge.com/markets/im-sorry-fed-has-run-out-road",
      "author": "zerohedge",
      "handle": "zerohedge",
      "createdAt": "2026-03-29T15:40:07+00:00",
      "createdAtMs": 1774798807000,
      "likes": 0,
      "retweets": 0,
      "url": "https://x.com/zerohedge/status/2038280048008913157#m",
      "avatar": null,
      "slot": "guaranteed",
      "slot_order": 1
    },
    {
      "id": "2038280058050109481",
      "text": "Price hikes have left large food brands vulnerable to competition. Shoppers have turned to cheaper private-label offerings from retailers such as Costco and Aldi, as well as upstarts https://www.economist.com/business/2026/03/25/big-foods-troubles-go-from-bad-to-worse?taid=69c947d95a6fb6000140e18f&utm_campaign=trueanthem&utm_medium=social&utm_source=twitter",
      "author": "TheEconomist",
      "handle": "TheEconomist",
      "createdAt": "2026-03-29T15:40:09+00:00",
      "createdAtMs": 1774798809000,
      "likes": 0,
      "retweets": 0,
      "url": "https://x.com/TheEconomist/status/2038280058050109481#m",
      "avatar": null,
      "slot": "guaranteed",
      "slot_order": 2
    },
    {
      "id": "2038263763963466022",
      "text": "Meanwhile, it has been a quiet weekend with continued escalation of Iran War strikes on both sides.\n\nWe just published our trades for premium members.\n\nSince 2020, our calls are up over +516%.\n\nSubscribe below to see how we are positioned into the week:\n\nhttp://thekobeissiletter.com/subscribe",
      "author": "KobeissiLetter",
      "handle": "KobeissiLetter",
      "createdAt": "2026-03-29T14:35:25+00:00",
      "createdAtMs": 1774794925000,
      "likes": 0,
      "retweets": 0,
      "url": "https://x.com/KobeissiLetter/status/2038263763963466022#m",
      "avatar": null,
      "slot": "guaranteed",
      "slot_order": 3
    },
    {
      "id": "2038245758189666694",
      "text": "Just woke up, nursing a hangover, but will do my best…. Come and join us as we do a Sunday Morning livestream from my living room…👇👇",
      "author": "hkuppy",
      "handle": "hkuppy",
      "createdAt": "2026-03-29T13:23:52+00:00",
      "createdAtMs": 1774790632000,
      "likes": 0,
      "retweets": 0,
      "url": "https://x.com/hkuppy/status/2038245758189666694#m",
      "avatar": null,
      "slot": "engagement",
      "slot_order": 4
    }
  ]
}