{
  "ok": true,
  "count": 4,
  "accountsWithPosts": 4,
  "fetchedAt": "2026-05-15T04:01:06.786754+00:00",
  "windowHours": 4,
  "curation": "guaranteed3_engagement1",
  "errors": [
    "WatcherGuru"
  ],
  "posts": [
    {
      "id": "2055133448184942849",
      "text": "JAPAN 20-YEAR YIELD RISES TO 3.605%, HIGHEST SINCE 1996",
      "author": "zerohedge",
      "handle": "zerohedge",
      "createdAt": "2026-05-15T03:49:31+00:00",
      "createdAtMs": 1778816971000,
      "likes": 0,
      "retweets": 0,
      "url": "https://x.com/zerohedge/status/2055133448184942849#m",
      "avatar": null,
      "slot": "guaranteed",
      "slot_order": 1
    },
    {
      "id": "2055131064549490891",
      "text": "Tanzanians had hoped Samia Suluhu Hassan would usher in a more open society. Now her repressive regime threatens the country’s achievements and its future  https://www.economist.com/leaders/2026/04/30/is-samia-suluhu-hassan-africas-most-disappointing-president?taid=6a069592e5e843000126f6dc&utm_campaign=editorial-social&utm_content=discovery.content&utm_medium=social-media.content.np&utm_source=twitter",
      "author": "TheEconomist",
      "handle": "TheEconomist",
      "createdAt": "2026-05-15T03:40:02+00:00",
      "createdAtMs": 1778816402000,
      "likes": 0,
      "retweets": 0,
      "url": "https://x.com/TheEconomist/status/2055131064549490891#m",
      "avatar": null,
      "slot": "guaranteed",
      "slot_order": 2
    },
    {
      "id": "2055131819427664230",
      "text": "It's like clockwork.\n\nThe 10Y Note Yield is now above 4.50% for the first time since June 2025.\n\nThis is the same level that resulted in President Trump's \"90-day tariff pause\" in April 2025.\n\nMeanwhile, rate HIKES are now the base case for the Fed's expected next move.\n\nAs a result, average rate on 30Y mortgage in the US is nearing 7% and inflation is at a fresh 3-year high.\n\nSeemingly overnight, \"higher for longer\" interest rate policy is back.\n\nHow long can this last?",
      "author": "KobeissiLetter",
      "handle": "KobeissiLetter",
      "createdAt": "2026-05-15T03:43:02+00:00",
      "createdAtMs": 1778816582000,
      "likes": 0,
      "retweets": 0,
      "url": "https://x.com/KobeissiLetter/status/2055131819427664230#m",
      "avatar": null,
      "slot": "guaranteed",
      "slot_order": 3
    },
    {
      "id": "2054928666597945748",
      "text": "It’s taken the entire evolution time scale of humans to get to the point where we can nano engineer nano materials with Ai nano technology. \n\nWe’ve just discovered that Turbostratic Fractal Graphene Aggregates are the very best primary atomic structure to nano engineer our future. \n\nPerspective is key.  $hg $hgraf is going to accomplish unprecedented achievements in partnership with major global manufacturers. \n\nInvestors must look at the key milestones that will be accomplished in the next year, three years, five years, decade and beyond.",
      "author": "BambroughKevin",
      "handle": "BambroughKevin",
      "createdAt": "2026-05-14T14:15:47+00:00",
      "createdAtMs": 1778768147000,
      "likes": 0,
      "retweets": 0,
      "url": "https://x.com/BambroughKevin/status/2054928666597945748#m",
      "avatar": null,
      "slot": "engagement",
      "slot_order": 4
    }
  ]
}