{
  "ok": true,
  "count": 4,
  "accountsWithPosts": 4,
  "fetchedAt": "2026-05-14T21:05:09.978972+00:00",
  "windowHours": 4,
  "curation": "guaranteed3_engagement1",
  "errors": [],
  "posts": [
    {
      "id": "2055025388703609176",
      "text": "Bad Signs: Christopher Nolan's \"The Odyssey\" Looks Like A Woke Disaster https://www.zerohedge.com/political/bad-signs-christopher-nolans-odyssey-looks-woke-disaster",
      "author": "zerohedge",
      "handle": "zerohedge",
      "createdAt": "2026-05-14T20:40:07+00:00",
      "createdAtMs": 1778791207000,
      "likes": 0,
      "retweets": 0,
      "url": "https://x.com/zerohedge/status/2055025388703609176#m",
      "avatar": null,
      "slot": "guaranteed",
      "slot_order": 1
    },
    {
      "id": "2055027887518994678",
      "text": "This what a giant precarious workforce reveals about the future of jobs https://www.economist.com/leaders/2025/09/18/chinas-200m-gig-workers-are-a-warning-for-the-world?taid=6a06357b32982f000154a9de&utm_campaign=editorial-social&utm_content=discovery.content&utm_medium=social-media.content.np&utm_source=twitter",
      "author": "TheEconomist",
      "handle": "TheEconomist",
      "createdAt": "2026-05-14T20:50:03+00:00",
      "createdAtMs": 1778791803000,
      "likes": 0,
      "retweets": 0,
      "url": "https://x.com/TheEconomist/status/2055027887518994678#m",
      "avatar": null,
      "slot": "guaranteed",
      "slot_order": 2
    },
    {
      "id": "2055017191011954727",
      "text": "BREAKING: The S&P 500 closes at its highest level on record, now up +19% since the March 30th bottom.\n\nThat's +$11 TRILLION in market cap in under 7 weeks.",
      "author": "KobeissiLetter",
      "handle": "KobeissiLetter",
      "createdAt": "2026-05-14T20:07:33+00:00",
      "createdAtMs": 1778789253000,
      "likes": 0,
      "retweets": 0,
      "url": "https://x.com/KobeissiLetter/status/2055017191011954727#m",
      "avatar": null,
      "slot": "guaranteed",
      "slot_order": 3
    },
    {
      "id": "2054928666597945748",
      "text": "It’s taken the entire evolution time scale of humans to get to the point where we can nano engineer nano materials with Ai nano technology. \n\nWe’ve just discovered that Turbostratic Fractal Graphene Aggregates are the very best primary atomic structure to nano engineer our future. \n\nPerspective is key.  $hg $hgraf is going to accomplish unprecedented achievements in partnership with major global manufacturers. \n\nInvestors must look at the key milestones that will be accomplished in the next year, three years, five years, decade and beyond.",
      "author": "BambroughKevin",
      "handle": "BambroughKevin",
      "createdAt": "2026-05-14T14:15:47+00:00",
      "createdAtMs": 1778768147000,
      "likes": 0,
      "retweets": 0,
      "url": "https://x.com/BambroughKevin/status/2054928666597945748#m",
      "avatar": null,
      "slot": "engagement",
      "slot_order": 4
    }
  ]
}