{
  "ok": true,
  "count": 4,
  "accountsWithPosts": 4,
  "fetchedAt": "2026-03-29T16:28:15.777694+00:00",
  "windowHours": 4,
  "curation": "guaranteed3_engagement1",
  "errors": [],
  "posts": [
    {
      "id": "2038288858807255206",
      "text": "Dealer Gamma Has Fallen Off A Cliff: Chief Goldman Equity Trader Warns 'Brace' For More Pain Into Month-End https://www.zerohedge.com/markets/dealer-gamma-has-fallen-cliff-chief-goldman-equity-trader-warns-brace-more-pain-month-end",
      "author": "zerohedge",
      "handle": "zerohedge",
      "createdAt": "2026-03-29T16:15:08+00:00",
      "createdAtMs": 1774800908000,
      "likes": 0,
      "retweets": 0,
      "url": "https://x.com/zerohedge/status/2038288858807255206#m",
      "avatar": null,
      "slot": "guaranteed",
      "slot_order": 1
    },
    {
      "id": "2038290128213336332",
      "text": "Britain’s government is overseeing what promises to be an undignified, if discreet, syphoning off of assets abroad. It is likely to be a long, laborious process https://www.economist.com/britain/2026/03/26/britains-diplomatic-footprint-is-diminishing?taid=69c9513ab7d88c00019f9705&utm_campaign=trueanthem&utm_medium=social&utm_source=twitter",
      "author": "TheEconomist",
      "handle": "TheEconomist",
      "createdAt": "2026-03-29T16:20:10+00:00",
      "createdAtMs": 1774801210000,
      "likes": 0,
      "retweets": 0,
      "url": "https://x.com/TheEconomist/status/2038290128213336332#m",
      "avatar": null,
      "slot": "guaranteed",
      "slot_order": 2
    },
    {
      "id": "2038287977294528924",
      "text": "BREAKING: Iran has drafted legislation to create the \"Hormuz Law\" which is expected create a formal toll system for the Strait of Hormuz.\n\nPreliminary details include:\n\n1. Hormuz Law to introduce fees on navigation and pollution in the Strait of Hormuz\n\n2. Draft legislation also includes creation of a \"regional fund\"\n\n3. The move is seen as an attempt to formalize long-term tolls on global shipping routes\n\n4. The US has called these tolls on the Strait of Hormuz both \"illegal\" and \"unacceptable\"\n\nThe Strait of Hormuz situation is becoming even more complicated.",
      "author": "KobeissiLetter",
      "handle": "KobeissiLetter",
      "createdAt": "2026-03-29T16:11:38+00:00",
      "createdAtMs": 1774800698000,
      "likes": 0,
      "retweets": 0,
      "url": "https://x.com/KobeissiLetter/status/2038287977294528924#m",
      "avatar": null,
      "slot": "guaranteed",
      "slot_order": 3
    },
    {
      "id": "2038245758189666694",
      "text": "Just woke up, nursing a hangover, but will do my best…. Come and join us as we do a Sunday Morning livestream from my living room…👇👇",
      "author": "hkuppy",
      "handle": "hkuppy",
      "createdAt": "2026-03-29T13:23:52+00:00",
      "createdAtMs": 1774790632000,
      "likes": 0,
      "retweets": 0,
      "url": "https://x.com/hkuppy/status/2038245758189666694#m",
      "avatar": null,
      "slot": "engagement",
      "slot_order": 4
    }
  ]
}