{
  "ok": true,
  "count": 4,
  "accountsWithPosts": 4,
  "fetchedAt": "2026-04-14T05:56:52.749737+00:00",
  "windowHours": 4,
  "curation": "guaranteed3_engagement1",
  "errors": [],
  "posts": [
    {
      "id": "2043897400431964396",
      "text": "\"Prices for Iranian Light have climbed since the war began at the end of February, with the grade recently offered at a small premium to ICE Brent\" - BBG",
      "author": "zerohedge",
      "handle": "zerohedge",
      "createdAt": "2026-04-14T03:41:28+00:00",
      "createdAtMs": 1776138088000,
      "likes": 0,
      "retweets": 0,
      "url": "https://x.com/zerohedge/status/2043897400431964396#m",
      "avatar": null,
      "slot": "guaranteed",
      "slot_order": 1
    },
    {
      "id": "2043927242615538111",
      "text": "The recipe for Nin Jiom Pei Pa Koa hasn’t changed since it was first concocted in the 1600s. Yet the sweet syrup is enjoying a renewed surge in popularity https://www.economist.com/business/2025/08/14/a-400-year-old-chinese-cough-syrup-is-winning-over-westerners?taid=69ddd333bd318b0001e8277c&utm_campaign=editorial-social&utm_content=discovery.content&utm_medium=social-media.content.np&utm_source=twitter",
      "author": "TheEconomist",
      "handle": "TheEconomist",
      "createdAt": "2026-04-14T05:40:03+00:00",
      "createdAtMs": 1776145203000,
      "likes": 0,
      "retweets": 0,
      "url": "https://x.com/TheEconomist/status/2043927242615538111#m",
      "avatar": null,
      "slot": "guaranteed",
      "slot_order": 2
    },
    {
      "id": "2043882612528238650",
      "text": "BREAKING: A new round of negotiations between the US and Iran may be held on Thursday, per AP.\n\nPresident Trump said that “we’ve been called by the other side” and “they want to work a deal.”",
      "author": "KobeissiLetter",
      "handle": "KobeissiLetter",
      "createdAt": "2026-04-14T02:42:42+00:00",
      "createdAtMs": 1776134562000,
      "likes": 0,
      "retweets": 0,
      "url": "https://x.com/KobeissiLetter/status/2043882612528238650#m",
      "avatar": null,
      "slot": "guaranteed",
      "slot_order": 3
    },
    {
      "id": "2043719623351103739",
      "text": "😂I'm waiting for this one...",
      "author": "hkuppy",
      "handle": "hkuppy",
      "createdAt": "2026-04-13T15:55:03+00:00",
      "createdAtMs": 1776095703000,
      "likes": 0,
      "retweets": 0,
      "url": "https://x.com/TylerHardt/status/2043719623351103739#m",
      "avatar": null,
      "slot": "engagement",
      "slot_order": 4
    }
  ]
}