{
  "Bangkok": {
    "name": "Bangkok",
    "flag": "🇹🇭",
    "lat": 13.7563,
    "lon": 100.5018,
    "tz_offset": 7,
    "temp": 27.5,
    "humidity": 73,
    "condition": "Overcast ☁️",
    "aqi": 49,
    "aqi_label": "Good",
    "ok": true,
    "cached_at": "2026-07-08T16:00:33.493499+00:00"
  },
  "Medellín": {
    "name": "Medellín",
    "flag": "🇨🇴",
    "lat": 6.2442,
    "lon": -75.5812,
    "tz_offset": -5,
    "temp": 30.6,
    "humidity": 35,
    "condition": "Overcast ☁️",
    "aqi": 48,
    "aqi_label": "Good",
    "ok": true,
    "cached_at": "2026-07-08T18:00:09.008352+00:00"
  },
  "Edmonton": {
    "name": "Edmonton",
    "flag": "🇨🇦",
    "lat": 53.5461,
    "lon": -113.4938,
    "tz_offset": -6,
    "temp": 20.6,
    "humidity": 74,
    "condition": "Drizzle 🌦",
    "aqi": 25,
    "aqi_label": "Good",
    "ok": true,
    "cached_at": "2026-07-08T18:00:10.146454+00:00"
  },
  "Montevideo": {
    "name": "Montevideo",
    "flag": "🇺🇾",
    "lat": -34.9011,
    "lon": -56.1645,
    "tz_offset": -3,
    "temp": 13.3,
    "humidity": 70,
    "condition": "Overcast ☁️",
    "aqi": 25,
    "aqi_label": "Good",
    "ok": true,
    "cached_at": "2026-07-08T18:00:11.088990+00:00"
  }
}