{
  "Bangkok": {
    "name": "Bangkok",
    "flag": "🇹🇭",
    "lat": 13.7563,
    "lon": 100.5018,
    "tz_offset": 7,
    "temp": 25.9,
    "humidity": 95,
    "condition": "Showers 🌦",
    "aqi": 49,
    "aqi_label": "Good",
    "ok": true,
    "cached_at": "2026-05-31T16:00:15.139705+00:00"
  },
  "Medellín": {
    "name": "Medellín",
    "flag": "🇨🇴",
    "lat": 6.2442,
    "lon": -75.5812,
    "tz_offset": -5,
    "temp": 29.0,
    "humidity": 45,
    "condition": "Overcast ☁️",
    "aqi": 40,
    "aqi_label": "Good",
    "ok": true,
    "cached_at": "2026-05-31T18:00:13.655957+00:00"
  },
  "Edmonton": {
    "name": "Edmonton",
    "flag": "🇨🇦",
    "lat": 53.5461,
    "lon": -113.4938,
    "tz_offset": -6,
    "temp": 9.1,
    "humidity": 89,
    "condition": "Rain 🌧",
    "aqi": 34,
    "aqi_label": "Good",
    "ok": true,
    "cached_at": "2026-05-31T18:00:20.627655+00:00"
  },
  "Montevideo": {
    "name": "Montevideo",
    "flag": "🇺🇾",
    "lat": -34.9011,
    "lon": -56.1645,
    "tz_offset": -3,
    "temp": 12.1,
    "humidity": 87,
    "condition": "Mainly Clear 🌤",
    "aqi": 51,
    "aqi_label": "Moderate",
    "ok": true,
    "cached_at": "2026-05-31T18:00:24.149754+00:00"
  }
}