{
  "Bangkok": {
    "name": "Bangkok",
    "flag": "🇹🇭",
    "lat": 13.7563,
    "lon": 100.5018,
    "tz_offset": 7,
    "temp": 31.5,
    "humidity": 63,
    "condition": "Light Drizzle 🌦",
    "aqi": 41,
    "aqi_label": "Good",
    "ok": true,
    "cached_at": "2026-05-28T10:00:14.090500+00:00"
  },
  "Medellín": {
    "name": "Medellín",
    "flag": "🇨🇴",
    "lat": 6.2442,
    "lon": -75.5812,
    "tz_offset": -5,
    "temp": 17.7,
    "humidity": 100,
    "condition": "Overcast ☁️",
    "aqi": 32,
    "aqi_label": "Good",
    "ok": true,
    "cached_at": "2026-05-28T10:00:21.427747+00:00"
  },
  "Edmonton": {
    "name": "Edmonton",
    "flag": "🇨🇦",
    "lat": 53.5461,
    "lon": -113.4938,
    "tz_offset": -6,
    "temp": 16.7,
    "humidity": 71,
    "condition": "Mainly Clear 🌤",
    "aqi": 38,
    "aqi_label": "Good",
    "ok": true,
    "cached_at": "2026-05-28T10:00:26.314391+00:00"
  },
  "Montevideo": {
    "name": "Montevideo",
    "flag": "🇺🇾",
    "lat": -34.9011,
    "lon": -56.1645,
    "tz_offset": -3,
    "temp": 11.4,
    "humidity": 96,
    "condition": "Mainly Clear 🌤",
    "aqi": 48,
    "aqi_label": "Good",
    "ok": true,
    "cached_at": "2026-05-28T10:00:30.056677+00:00"
  }
}